setup.py
csvddf/__init__.py
csvddf.egg-info/PKG-INFO
csvddf.egg-info/SOURCES.txt
csvddf.egg-info/dependency_links.txt
csvddf.egg-info/top_level.txt