Metadata-Version: 1.0
Name: csvddf
Version: 1.0
Summary: Python library for dealing with CSVDDF files
Home-page: UNKNOWN
Author: Martin Keegan
Author-email: martin.keegan@okfn.org
License: Apache Licence v2.0
Platform: UNKNOWN
